
[
  {
    "id": 1,
    "title": "Casual Summer Dress",
    "occasions": ["Casual"],
    "color": "Yellow",
    "style": "Boho Chic",
    "price": "₹1,499",
    "image": "https://images.pexels.com/photos/1234567/pexels-photo-1234567.jpeg",
    "description": "A light, floral summer dress perfect for warm weather outings.",
    "recommended_jewelry": ["Gold hoop earrings", "Layered bracelets", "Delicate necklace"],
    "recommended_shoes": ["Tan sandals", "White espadrilles"],
    "recommended_accessories": ["Woven straw bag", "Sun hat", "Sunglasses"]
  },
  {
    "id": 2,
    "title": "Formal Blazer Set",
    "occasions": ["Formal"],
    "color": "Navy Blue",
    "style": "Business Classic",
    "price": "₹3,999",
    "image": "https://images.pexels.com/photos/2345678/pexels-photo-2345678.jpeg",
    "description": "A sleek navy blue blazer with matching trousers for office meetings.",
    "recommended_jewelry": ["Silver cufflinks", "Classic watch"],
    "recommended_shoes": ["Black leather oxford shoes"],
    "recommended_accessories": ["Leather briefcase", "Tie or pocket square"]
  },
  {
    "id": 3,
    "title": "Party Gown",
    "occasions": ["Party"],
    "color": "Red",
    "style": "Glamour",
    "price": "₹5,499",
    "image": "https://images.pexels.com/photos/3456789/pexels-photo-3456789.jpeg",
    "description": "An elegant red gown with sequins — perfect for evening parties.",
    "recommended_jewelry": ["Diamond stud earrings", "Gold bracelet", "Statement necklace"],
    "recommended_shoes": ["Silver stiletto heels", "Red pumps"],
    "recommended_accessories": ["Clutch bag", "Elegant shawl"]
  },
  {
    "id": 4,
    "title": "Ethnic Kurta Set",
    "occasions": ["Traditional"],
    "color": "Maroon",
    "style": "Traditional",
    "price": "₹2,599",
    "image": "https://images.pexels.com/photos/4567890/pexels-photo-4567890.jpeg",
    "description": "Elegant maroon kurta set for weddings and festive celebrations.",
    "recommended_jewelry": ["Gold bracelet", "Traditional watch"],
    "recommended_shoes": ["Mojaris", "Kolhapuri sandals"],
    "recommended_accessories": ["Embroidered stole", "Festive dupatta"]
  },
  {
    "id": 5,
    "title": "Casual Denim Outfit",
    "occasions": ["Casual"],
    "color": "Blue",
    "style": "Street Denim",
    "price": "₹2,199",
    "image": "https://images.pexels.com/photos/5678901/pexels-photo-5678901.jpeg",
    "description": "Blue denim jacket with white t-shirt and jeans.",
    "recommended_jewelry": ["Silver hoops", "Minimalist rings"],
    "recommended_shoes": ["White sneakers", "Ankle boots"],
    "recommended_accessories": ["Crossbody bag", "Sunglasses"]
  },
  {
    "id": 6,
    "title": "Formal Pencil Skirt Suit",
    "occasions": ["Formal"],
    "color": "Grey",
    "style": "Business Formal",
    "price": "₹3,299",
    "image": "https://images.pexels.com/photos/6789012/pexels-photo-6789012.jpeg",
    "description": "Professional grey skirt suit ideal for office meetings.",
    "recommended_jewelry": ["Pearl earrings", "Silver watch"],
    "recommended_shoes": ["Black pumps", "Loafers"],
    "recommended_accessories": ["Leather tote", "Minimalist belt"]
  },
  {
    "id": 7,
    "title": "Cocktail Dress",
    "occasions": ["Party"],
    "color": "Black",
    "style": "Elegant Night",
    "price": "₹4,899",
    "image": "https://images.pexels.com/photos/7890123/pexels-photo-7890123.jpeg",
    "description": "Chic black cocktail dress for evening and party events.",
    "recommended_jewelry": ["Silver earrings", "Diamond bracelet", "Statement ring"],
    "recommended_shoes": ["Black stilettos", "Metallic heels"],
    "recommended_accessories": ["Clutch bag", "Evening shawl"]
  },
  {
    "id": 8,
    "title": "Traditional Saree",
    "occasions": ["Traditional"],
    "color": "Royal Blue",
    "style": "Elegant",
    "price": "₹3,499",
    "image": "https://images.pexels.com/photos/8901234/pexels-photo-8901234.jpeg",
    "description": "Graceful saree with golden embroidery for evening events.",
    "recommended_jewelry": ["Gold jhumkas", "Bangles", "Statement ring"],
    "recommended_shoes": ["Golden heels", "Embellished flats"],
    "recommended_accessories": ["Clutch bag", "Hair accessories"]
  },
  {
    "id": 9,
    "title": "Business Casual Blazer",
    "occasions": ["Formal"],
    "color": "Charcoal Grey",
    "style": "Business Casual",
    "price": "₹2,799",
    "image": "https://images.pexels.com/photos/9012345/pexels-photo-9012345.jpeg",
    "description": "Charcoal grey blazer perfect for business casual settings.",
    "recommended_jewelry": ["Silver cufflinks", "Leather strap watch"],
    "recommended_shoes": ["Brown loafers", "Derby shoes"],
    "recommended_accessories": ["Leather belt", "Briefcase"]
  },
  {
    "id": 10,
    "title": "Floral Maxi Dress",
    "occasions": ["Casual"],
    "color": "Pink",
    "style": "Boho Chic",
    "price": "₹1,999",
    "image": "https://images.pexels.com/photos/1234568/pexels-photo-1234568.jpeg",
    "description": "Flowy pink maxi dress with floral patterns.",
    "recommended_jewelry": ["Gold bangles", "Layered necklaces"],
    "recommended_shoes": ["Flat sandals", "Wedge heels"],
    "recommended_accessories": ["Wide-brim hat", "Tote bag"]
  },
  {
    "id": 11,
    "title": "Tuxedo Suit",
    "occasions": ["Formal"],
    "color": "Black",
    "style": "Classic",
    "price": "₹7,499",
    "image": "https://images.pexels.com/photos/2345679/pexels-photo-2345679.jpeg",
    "description": "Classic black tuxedo suit for formal events.",
    "recommended_jewelry": ["Cufflinks", "Pocket watch"],
    "recommended_shoes": ["Black patent leather shoes"],
    "recommended_accessories": ["Silk tie", "Pocket square"]
  },
  {
    "id": 12,
    "title": "Silk Evening Gown",
    "occasions": ["Party"],
    "color": "Emerald Green",
    "style": "Elegant",
    "price": "₹6,999",
    "image": "https://images.pexels.com/photos/3456790/pexels-photo-3456790.jpeg",
    "description": "Luxurious silk gown with a deep V-neckline.",
    "recommended_jewelry": ["Diamond necklace", "Emerald earrings"],
    "recommended_shoes": ["Nude heels", "Strappy sandals"],
    "recommended_accessories": ["Clutch bag", "Shawl"]
  },
  {
    "id": 13,
    "title": "Churidar Kurta Set",
    "occasions": ["Traditional"],
    "color": "Ivory",
    "style": "Traditional",
    "price": "₹2,199",
    "image": "https://images.pexels.com/photos/4567891/pexels-photo-4567891.jpeg",
    "description": "Elegant ivory churidar kurta set for festive occasions.",
    "recommended_jewelry": ["Gold jhumkas", "Bangles"],
    "recommended_shoes": ["Mojaris", "Kolhapuri sandals"],
    "recommended_accessories": ["Dupatta", "Clutch bag"]
  },
  {
    "id": 14,
    "title": "Striped Shirt and Chinos",
    "occasions": ["Casual"],
    "color": "Blue and Beige",
    "style": "Smart Casual",
    "price": "₹2,499",
    "image": "https://images.pexels.com/photos/5678902/pexels-photo-5678902.jpeg",
    "description": "Blue striped shirt paired with beige chinos.",
    "recommended_jewelry": ["Leather strap watch", "Minimalist ring"],
    "recommended_shoes": ["Brown loafers", "White sneakers"],
    "recommended_accessories": ["Leather belt", "Messenger bag"]
  },
  {
    "id": 15,
    "title": "Pleated Skirt and Blouse",
    "occasions": ["Formal"],
    "color": "Black and White",
    "style": "Business Casual",
    "price": "₹2,199",
    "image": "https://images.pexels.com/photos/6789013/pexels-photo-6789013.jpeg",
    "description": "Black pleated skirt paired with a white blouse.",
    "recommended_jewelry": ["Silver earrings", "Watch"],
    "recommended_shoes": ["Black pumps", "Ballet flats"],
    "recommended_accessories": ["Leather tote", "Scarf"]
  }
]
